{
  "metadata": {
    "dataset": "openfootball_world_cup_2026",
    "source_name": "OpenFootball World Cup 2026 (CC0)",
    "source_url": "https://raw.githubusercontent.com/openfootball/worldcup.json/master/2026/worldcup.json",
    "source_updated_at": "2026-06-30T17:42:19.914256+00:00",
    "processed_at": "2026-06-30T17:42:19.914256+00:00",
    "timezone": "Europe/Oslo",
    "is_live_data": false,
    "skipped_unresolved_matches": 16,
    "notes": [
      "OpenFootball CC0-snapshot med komplett terminliste.",
      "Resultater oppdateres periodisk og er ikke sekund-for-sekund live.",
      "FIFA er autoritativ kilde ved eventuelle avvik."
    ]
  },
  "matches": [
    {
      "id": 10001,
      "match_number": null,
      "tournament_year": 2026,
      "stage": "Group stage",
      "group_name": "A",
      "home_team_id": 17,
      "away_team_id": 18,
      "kickoff_at": "2026-06-11T19:00:00+00:00",
      "stadium": "Mexico City",
      "city": "Mexico City",
      "status": "finished",
      "home_score": 2,
      "away_score": 0,
      "home_penalty_score": null,
      "away_penalty_score": null
    },
    {
      "id": 10002,
      "match_number": null,
      "tournament_year": 2026,
      "stage": "Group stage",
      "group_name": "A",
      "home_team_id": 19,
      "away_team_id": 20,
      "kickoff_at": "2026-06-12T02:00:00+00:00",
      "stadium": "Guadalajara (Zapopan)",
      "city": "Guadalajara (Zapopan)",
      "status": "finished",
      "home_score": 2,
      "away_score": 1,
      "home_penalty_score": null,
      "away_penalty_score": null
    },
    {
      "id": 10007,
      "match_number": null,
      "tournament_year": 2026,
      "stage": "Group stage",
      "group_name": "B",
      "home_team_id": 21,
      "away_team_id": 22,
      "kickoff_at": "2026-06-12T19:00:00+00:00",
      "stadium": "Toronto",
      "city": "Toronto",
      "status": "finished",
      "home_score": 1,
      "away_score": 1,
      "home_penalty_score": null,
      "away_penalty_score": null
    },
    {
      "id": 10019,
      "match_number": null,
      "tournament_year": 2026,
      "stage": "Group stage",
      "group_name": "D",
      "home_team_id": 29,
      "away_team_id": 30,
      "kickoff_at": "2026-06-13T01:00:00+00:00",
      "stadium": "Los Angeles (Inglewood)",
      "city": "Los Angeles (Inglewood)",
      "status": "finished",
      "home_score": 4,
      "away_score": 1,
      "home_penalty_score": null,
      "away_penalty_score": null
    },
    {
      "id": 10008,
      "match_number": null,
      "tournament_year": 2026,
      "stage": "Group stage",
      "group_name": "B",
      "home_team_id": 23,
      "away_team_id": 24,
      "kickoff_at": "2026-06-13T19:00:00+00:00",
      "stadium": "San Francisco Bay Area (Santa Clara)",
      "city": "San Francisco Bay Area (Santa Clara)",
      "status": "finished",
      "home_score": 1,
      "away_score": 1,
      "home_penalty_score": null,
      "away_penalty_score": null
    },
    {
      "id": 10013,
      "match_number": null,
      "tournament_year": 2026,
      "stage": "Group stage",
      "group_name": "C",
      "home_team_id": 25,
      "away_team_id": 26,
      "kickoff_at": "2026-06-13T22:00:00+00:00",
      "stadium": "New York/New Jersey (East Rutherford)",
      "city": "New York/New Jersey (East Rutherford)",
      "status": "finished",
      "home_score": 1,
      "away_score": 1,
      "home_penalty_score": null,
      "away_penalty_score": null
    },
    {
      "id": 10014,
      "match_number": null,
      "tournament_year": 2026,
      "stage": "Group stage",
      "group_name": "C",
      "home_team_id": 27,
      "away_team_id": 28,
      "kickoff_at": "2026-06-14T01:00:00+00:00",
      "stadium": "Boston (Foxborough)",
      "city": "Boston (Foxborough)",
      "status": "finished",
      "home_score": 0,
      "away_score": 1,
      "home_penalty_score": null,
      "away_penalty_score": null
    },
    {
      "id": 10020,
      "match_number": null,
      "tournament_year": 2026,
      "stage": "Group stage",
      "group_name": "D",
      "home_team_id": 31,
      "away_team_id": 32,
      "kickoff_at": "2026-06-14T04:00:00+00:00",
      "stadium": "Vancouver",
      "city": "Vancouver",
      "status": "finished",
      "home_score": 2,
      "away_score": 0,
      "home_penalty_score": null,
      "away_penalty_score": null
    },
    {
      "id": 10025,
      "match_number": null,
      "tournament_year": 2026,
      "stage": "Group stage",
      "group_name": "E",
      "home_team_id": 33,
      "away_team_id": 34,
      "kickoff_at": "2026-06-14T17:00:00+00:00",
      "stadium": "Houston",
      "city": "Houston",
      "status": "finished",
      "home_score": 7,
      "away_score": 1,
      "home_penalty_score": null,
      "away_penalty_score": null
    },
    {
      "id": 10031,
      "match_number": null,
      "tournament_year": 2026,
      "stage": "Group stage",
      "group_name": "F",
      "home_team_id": 37,
      "away_team_id": 38,
      "kickoff_at": "2026-06-14T20:00:00+00:00",
      "stadium": "Dallas (Arlington)",
      "city": "Dallas (Arlington)",
      "status": "finished",
      "home_score": 2,
      "away_score": 2,
      "home_penalty_score": null,
      "away_penalty_score": null
    },
    {
      "id": 10026,
      "match_number": null,
      "tournament_year": 2026,
      "stage": "Group stage",
      "group_name": "E",
      "home_team_id": 35,
      "away_team_id": 36,
      "kickoff_at": "2026-06-14T23:00:00+00:00",
      "stadium": "Philadelphia",
      "city": "Philadelphia",
      "status": "finished",
      "home_score": 1,
      "away_score": 0,
      "home_penalty_score": null,
      "away_penalty_score": null
    },
    {
      "id": 10032,
      "match_number": null,
      "tournament_year": 2026,
      "stage": "Group stage",
      "group_name": "F",
      "home_team_id": 39,
      "away_team_id": 40,
      "kickoff_at": "2026-06-15T02:00:00+00:00",
      "stadium": "Monterrey (Guadalupe)",
      "city": "Monterrey (Guadalupe)",
      "status": "finished",
      "home_score": 5,
      "away_score": 1,
      "home_penalty_score": null,
      "away_penalty_score": null
    },
    {
      "id": 10043,
      "match_number": null,
      "tournament_year": 2026,
      "stage": "Group stage",
      "group_name": "H",
      "home_team_id": 45,
      "away_team_id": 46,
      "kickoff_at": "2026-06-15T16:00:00+00:00",
      "stadium": "Atlanta",
      "city": "Atlanta",
      "status": "finished",
      "home_score": 0,
      "away_score": 0,
      "home_penalty_score": null,
      "away_penalty_score": null
    },
    {
      "id": 10037,
      "match_number": null,
      "tournament_year": 2026,
      "stage": "Group stage",
      "group_name": "G",
      "home_team_id": 41,
      "away_team_id": 42,
      "kickoff_at": "2026-06-15T19:00:00+00:00",
      "stadium": "Seattle",
      "city": "Seattle",
      "status": "finished",
      "home_score": 1,
      "away_score": 1,
      "home_penalty_score": null,
      "away_penalty_score": null
    },
    {
      "id": 10044,
      "match_number": null,
      "tournament_year": 2026,
      "stage": "Group stage",
      "group_name": "H",
      "home_team_id": 47,
      "away_team_id": 48,
      "kickoff_at": "2026-06-15T22:00:00+00:00",
      "stadium": "Miami (Miami Gardens)",
      "city": "Miami (Miami Gardens)",
      "status": "finished",
      "home_score": 1,
      "away_score": 1,
      "home_penalty_score": null,
      "away_penalty_score": null
    },
    {
      "id": 10038,
      "match_number": null,
      "tournament_year": 2026,
      "stage": "Group stage",
      "group_name": "G",
      "home_team_id": 43,
      "away_team_id": 44,
      "kickoff_at": "2026-06-16T01:00:00+00:00",
      "stadium": "Los Angeles (Inglewood)",
      "city": "Los Angeles (Inglewood)",
      "status": "finished",
      "home_score": 2,
      "away_score": 2,
      "home_penalty_score": null,
      "away_penalty_score": null
    },
    {
      "id": 1,
      "match_number": null,
      "tournament_year": 2026,
      "stage": "Group stage",
      "group_name": "I",
      "home_team_id": 2,
      "away_team_id": 3,
      "kickoff_at": "2026-06-16T19:00:00+00:00",
      "stadium": "New York/New Jersey (East Rutherford)",
      "city": "New York/New Jersey (East Rutherford)",
      "status": "finished",
      "home_score": 3,
      "away_score": 1,
      "home_penalty_score": null,
      "away_penalty_score": null
    },
    {
      "id": 2,
      "match_number": null,
      "tournament_year": 2026,
      "stage": "Group stage",
      "group_name": "I",
      "home_team_id": 4,
      "away_team_id": 1,
      "kickoff_at": "2026-06-16T22:00:00+00:00",
      "stadium": "Boston (Foxborough)",
      "city": "Boston (Foxborough)",
      "status": "finished",
      "home_score": 1,
      "away_score": 4,
      "home_penalty_score": null,
      "away_penalty_score": null
    },
    {
      "id": 7,
      "match_number": null,
      "tournament_year": 2026,
      "stage": "Group stage",
      "group_name": "J",
      "home_team_id": 5,
      "away_team_id": 6,
      "kickoff_at": "2026-06-17T01:00:00+00:00",
      "stadium": "Kansas City",
      "city": "Kansas City",
      "status": "finished",
      "home_score": 3,
      "away_score": 0,
      "home_penalty_score": null,
      "away_penalty_score": null
    },
    {
      "id": 8,
      "match_number": null,
      "tournament_year": 2026,
      "stage": "Group stage",
      "group_name": "J",
      "home_team_id": 7,
      "away_team_id": 8,
      "kickoff_at": "2026-06-17T04:00:00+00:00",
      "stadium": "San Francisco Bay Area (Santa Clara)",
      "city": "San Francisco Bay Area (Santa Clara)",
      "status": "finished",
      "home_score": 3,
      "away_score": 1,
      "home_penalty_score": null,
      "away_penalty_score": null
    },
    {
      "id": 13,
      "match_number": null,
      "tournament_year": 2026,
      "stage": "Group stage",
      "group_name": "K",
      "home_team_id": 9,
      "away_team_id": 10,
      "kickoff_at": "2026-06-17T17:00:00+00:00",
      "stadium": "Houston",
      "city": "Houston",
      "status": "finished",
      "home_score": 1,
      "away_score": 1,
      "home_penalty_score": null,
      "away_penalty_score": null
    },
    {
      "id": 18,
      "match_number": null,
      "tournament_year": 2026,
      "stage": "Group stage",
      "group_name": "L",
      "home_team_id": 13,
      "away_team_id": 14,
      "kickoff_at": "2026-06-17T20:00:00+00:00",
      "stadium": "Dallas (Arlington)",
      "city": "Dallas (Arlington)",
      "status": "finished",
      "home_score": 4,
      "away_score": 2,
      "home_penalty_score": null,
      "away_penalty_score": null
    },
    {
      "id": 10068,
      "match_number": null,
      "tournament_year": 2026,
      "stage": "Group stage",
      "group_name": "L",
      "home_team_id": 15,
      "away_team_id": 16,
      "kickoff_at": "2026-06-17T23:00:00+00:00",
      "stadium": "Toronto",
      "city": "Toronto",
      "status": "finished",
      "home_score": 1,
      "away_score": 0,
      "home_penalty_score": null,
      "away_penalty_score": null
    },
    {
      "id": 10062,
      "match_number": null,
      "tournament_year": 2026,
      "stage": "Group stage",
      "group_name": "K",
      "home_team_id": 11,
      "away_team_id": 12,
      "kickoff_at": "2026-06-18T02:00:00+00:00",
      "stadium": "Mexico City",
      "city": "Mexico City",
      "status": "finished",
      "home_score": 1,
      "away_score": 3,
      "home_penalty_score": null,
      "away_penalty_score": null
    },
    {
      "id": 10003,
      "match_number": null,
      "tournament_year": 2026,
      "stage": "Group stage",
      "group_name": "A",
      "home_team_id": 20,
      "away_team_id": 18,
      "kickoff_at": "2026-06-18T16:00:00+00:00",
      "stadium": "Atlanta",
      "city": "Atlanta",
      "status": "finished",
      "home_score": 1,
      "away_score": 1,
      "home_penalty_score": null,
      "away_penalty_score": null
    },
    {
      "id": 10009,
      "match_number": null,
      "tournament_year": 2026,
      "stage": "Group stage",
      "group_name": "B",
      "home_team_id": 24,
      "away_team_id": 22,
      "kickoff_at": "2026-06-18T19:00:00+00:00",
      "stadium": "Los Angeles (Inglewood)",
      "city": "Los Angeles (Inglewood)",
      "status": "finished",
      "home_score": 4,
      "away_score": 1,
      "home_penalty_score": null,
      "away_penalty_score": null
    },
    {
      "id": 10010,
      "match_number": null,
      "tournament_year": 2026,
      "stage": "Group stage",
      "group_name": "B",
      "home_team_id": 21,
      "away_team_id": 23,
      "kickoff_at": "2026-06-18T22:00:00+00:00",
      "stadium": "Vancouver",
      "city": "Vancouver",
      "status": "finished",
      "home_score": 6,
      "away_score": 0,
      "home_penalty_score": null,
      "away_penalty_score": null
    },
    {
      "id": 10004,
      "match_number": null,
      "tournament_year": 2026,
      "stage": "Group stage",
      "group_name": "A",
      "home_team_id": 17,
      "away_team_id": 19,
      "kickoff_at": "2026-06-19T01:00:00+00:00",
      "stadium": "Guadalajara (Zapopan)",
      "city": "Guadalajara (Zapopan)",
      "status": "finished",
      "home_score": 1,
      "away_score": 0,
      "home_penalty_score": null,
      "away_penalty_score": null
    },
    {
      "id": 10021,
      "match_number": null,
      "tournament_year": 2026,
      "stage": "Group stage",
      "group_name": "D",
      "home_team_id": 29,
      "away_team_id": 31,
      "kickoff_at": "2026-06-19T19:00:00+00:00",
      "stadium": "Seattle",
      "city": "Seattle",
      "status": "finished",
      "home_score": 2,
      "away_score": 0,
      "home_penalty_score": null,
      "away_penalty_score": null
    },
    {
      "id": 10015,
      "match_number": null,
      "tournament_year": 2026,
      "stage": "Group stage",
      "group_name": "C",
      "home_team_id": 28,
      "away_team_id": 26,
      "kickoff_at": "2026-06-19T22:00:00+00:00",
      "stadium": "Boston (Foxborough)",
      "city": "Boston (Foxborough)",
      "status": "finished",
      "home_score": 0,
      "away_score": 1,
      "home_penalty_score": null,
      "away_penalty_score": null
    },
    {
      "id": 10016,
      "match_number": null,
      "tournament_year": 2026,
      "stage": "Group stage",
      "group_name": "C",
      "home_team_id": 25,
      "away_team_id": 27,
      "kickoff_at": "2026-06-20T00:30:00+00:00",
      "stadium": "Philadelphia",
      "city": "Philadelphia",
      "status": "finished",
      "home_score": 3,
      "away_score": 0,
      "home_penalty_score": null,
      "away_penalty_score": null
    },
    {
      "id": 10022,
      "match_number": null,
      "tournament_year": 2026,
      "stage": "Group stage",
      "group_name": "D",
      "home_team_id": 32,
      "away_team_id": 30,
      "kickoff_at": "2026-06-20T03:00:00+00:00",
      "stadium": "San Francisco Bay Area (Santa Clara)",
      "city": "San Francisco Bay Area (Santa Clara)",
      "status": "finished",
      "home_score": 0,
      "away_score": 1,
      "home_penalty_score": null,
      "away_penalty_score": null
    },
    {
      "id": 10033,
      "match_number": null,
      "tournament_year": 2026,
      "stage": "Group stage",
      "group_name": "F",
      "home_team_id": 37,
      "away_team_id": 39,
      "kickoff_at": "2026-06-20T17:00:00+00:00",
      "stadium": "Houston",
      "city": "Houston",
      "status": "finished",
      "home_score": 5,
      "away_score": 1,
      "home_penalty_score": null,
      "away_penalty_score": null
    },
    {
      "id": 10027,
      "match_number": null,
      "tournament_year": 2026,
      "stage": "Group stage",
      "group_name": "E",
      "home_team_id": 33,
      "away_team_id": 35,
      "kickoff_at": "2026-06-20T20:00:00+00:00",
      "stadium": "Toronto",
      "city": "Toronto",
      "status": "finished",
      "home_score": 2,
      "away_score": 1,
      "home_penalty_score": null,
      "away_penalty_score": null
    },
    {
      "id": 10028,
      "match_number": null,
      "tournament_year": 2026,
      "stage": "Group stage",
      "group_name": "E",
      "home_team_id": 36,
      "away_team_id": 34,
      "kickoff_at": "2026-06-21T00:00:00+00:00",
      "stadium": "Kansas City",
      "city": "Kansas City",
      "status": "finished",
      "home_score": 0,
      "away_score": 0,
      "home_penalty_score": null,
      "away_penalty_score": null
    },
    {
      "id": 10034,
      "match_number": null,
      "tournament_year": 2026,
      "stage": "Group stage",
      "group_name": "F",
      "home_team_id": 40,
      "away_team_id": 38,
      "kickoff_at": "2026-06-21T04:00:00+00:00",
      "stadium": "Monterrey (Guadalupe)",
      "city": "Monterrey (Guadalupe)",
      "status": "finished",
      "home_score": 0,
      "away_score": 4,
      "home_penalty_score": null,
      "away_penalty_score": null
    },
    {
      "id": 10045,
      "match_number": null,
      "tournament_year": 2026,
      "stage": "Group stage",
      "group_name": "H",
      "home_team_id": 45,
      "away_team_id": 47,
      "kickoff_at": "2026-06-21T16:00:00+00:00",
      "stadium": "Atlanta",
      "city": "Atlanta",
      "status": "finished",
      "home_score": 4,
      "away_score": 0,
      "home_penalty_score": null,
      "away_penalty_score": null
    },
    {
      "id": 10039,
      "match_number": null,
      "tournament_year": 2026,
      "stage": "Group stage",
      "group_name": "G",
      "home_team_id": 41,
      "away_team_id": 43,
      "kickoff_at": "2026-06-21T19:00:00+00:00",
      "stadium": "Los Angeles (Inglewood)",
      "city": "Los Angeles (Inglewood)",
      "status": "finished",
      "home_score": 0,
      "away_score": 0,
      "home_penalty_score": null,
      "away_penalty_score": null
    },
    {
      "id": 10046,
      "match_number": null,
      "tournament_year": 2026,
      "stage": "Group stage",
      "group_name": "H",
      "home_team_id": 48,
      "away_team_id": 46,
      "kickoff_at": "2026-06-21T22:00:00+00:00",
      "stadium": "Miami (Miami Gardens)",
      "city": "Miami (Miami Gardens)",
      "status": "finished",
      "home_score": 2,
      "away_score": 2,
      "home_penalty_score": null,
      "away_penalty_score": null
    },
    {
      "id": 10040,
      "match_number": null,
      "tournament_year": 2026,
      "stage": "Group stage",
      "group_name": "G",
      "home_team_id": 44,
      "away_team_id": 42,
      "kickoff_at": "2026-06-22T01:00:00+00:00",
      "stadium": "Vancouver",
      "city": "Vancouver",
      "status": "finished",
      "home_score": 1,
      "away_score": 3,
      "home_penalty_score": null,
      "away_penalty_score": null
    },
    {
      "id": 9,
      "match_number": null,
      "tournament_year": 2026,
      "stage": "Group stage",
      "group_name": "J",
      "home_team_id": 5,
      "away_team_id": 7,
      "kickoff_at": "2026-06-22T17:00:00+00:00",
      "stadium": "Dallas (Arlington)",
      "city": "Dallas (Arlington)",
      "status": "finished",
      "home_score": 2,
      "away_score": 0,
      "home_penalty_score": null,
      "away_penalty_score": null
    },
    {
      "id": 4,
      "match_number": null,
      "tournament_year": 2026,
      "stage": "Group stage",
      "group_name": "I",
      "home_team_id": 2,
      "away_team_id": 4,
      "kickoff_at": "2026-06-22T21:00:00+00:00",
      "stadium": "Philadelphia",
      "city": "Philadelphia",
      "status": "finished",
      "home_score": 3,
      "away_score": 0,
      "home_penalty_score": null,
      "away_penalty_score": null
    },
    {
      "id": 3,
      "match_number": null,
      "tournament_year": 2026,
      "stage": "Group stage",
      "group_name": "I",
      "home_team_id": 1,
      "away_team_id": 3,
      "kickoff_at": "2026-06-23T00:00:00+00:00",
      "stadium": "New York/New Jersey (East Rutherford)",
      "city": "New York/New Jersey (East Rutherford)",
      "status": "finished",
      "home_score": 3,
      "away_score": 2,
      "home_penalty_score": null,
      "away_penalty_score": null
    },
    {
      "id": 10,
      "match_number": null,
      "tournament_year": 2026,
      "stage": "Group stage",
      "group_name": "J",
      "home_team_id": 8,
      "away_team_id": 6,
      "kickoff_at": "2026-06-23T03:00:00+00:00",
      "stadium": "San Francisco Bay Area (Santa Clara)",
      "city": "San Francisco Bay Area (Santa Clara)",
      "status": "finished",
      "home_score": 1,
      "away_score": 2,
      "home_penalty_score": null,
      "away_penalty_score": null
    },
    {
      "id": 14,
      "match_number": null,
      "tournament_year": 2026,
      "stage": "Group stage",
      "group_name": "K",
      "home_team_id": 9,
      "away_team_id": 11,
      "kickoff_at": "2026-06-23T17:00:00+00:00",
      "stadium": "Houston",
      "city": "Houston",
      "status": "finished",
      "home_score": 5,
      "away_score": 0,
      "home_penalty_score": null,
      "away_penalty_score": null
    },
    {
      "id": 19,
      "match_number": null,
      "tournament_year": 2026,
      "stage": "Group stage",
      "group_name": "L",
      "home_team_id": 13,
      "away_team_id": 15,
      "kickoff_at": "2026-06-23T20:00:00+00:00",
      "stadium": "Boston (Foxborough)",
      "city": "Boston (Foxborough)",
      "status": "finished",
      "home_score": 0,
      "away_score": 0,
      "home_penalty_score": null,
      "away_penalty_score": null
    },
    {
      "id": 20,
      "match_number": null,
      "tournament_year": 2026,
      "stage": "Group stage",
      "group_name": "L",
      "home_team_id": 16,
      "away_team_id": 14,
      "kickoff_at": "2026-06-23T23:00:00+00:00",
      "stadium": "Toronto",
      "city": "Toronto",
      "status": "finished",
      "home_score": 0,
      "away_score": 1,
      "home_penalty_score": null,
      "away_penalty_score": null
    },
    {
      "id": 15,
      "match_number": null,
      "tournament_year": 2026,
      "stage": "Group stage",
      "group_name": "K",
      "home_team_id": 12,
      "away_team_id": 10,
      "kickoff_at": "2026-06-24T02:00:00+00:00",
      "stadium": "Guadalajara (Zapopan)",
      "city": "Guadalajara (Zapopan)",
      "status": "finished",
      "home_score": 1,
      "away_score": 0,
      "home_penalty_score": null,
      "away_penalty_score": null
    },
    {
      "id": 10011,
      "match_number": null,
      "tournament_year": 2026,
      "stage": "Group stage",
      "group_name": "B",
      "home_team_id": 24,
      "away_team_id": 21,
      "kickoff_at": "2026-06-24T19:00:00+00:00",
      "stadium": "Vancouver",
      "city": "Vancouver",
      "status": "finished",
      "home_score": 2,
      "away_score": 1,
      "home_penalty_score": null,
      "away_penalty_score": null
    },
    {
      "id": 10012,
      "match_number": null,
      "tournament_year": 2026,
      "stage": "Group stage",
      "group_name": "B",
      "home_team_id": 22,
      "away_team_id": 23,
      "kickoff_at": "2026-06-24T19:00:00+00:00",
      "stadium": "Seattle",
      "city": "Seattle",
      "status": "finished",
      "home_score": 3,
      "away_score": 1,
      "home_penalty_score": null,
      "away_penalty_score": null
    },
    {
      "id": 10017,
      "match_number": null,
      "tournament_year": 2026,
      "stage": "Group stage",
      "group_name": "C",
      "home_team_id": 28,
      "away_team_id": 25,
      "kickoff_at": "2026-06-24T22:00:00+00:00",
      "stadium": "Miami (Miami Gardens)",
      "city": "Miami (Miami Gardens)",
      "status": "finished",
      "home_score": 0,
      "away_score": 3,
      "home_penalty_score": null,
      "away_penalty_score": null
    },
    {
      "id": 10018,
      "match_number": null,
      "tournament_year": 2026,
      "stage": "Group stage",
      "group_name": "C",
      "home_team_id": 26,
      "away_team_id": 27,
      "kickoff_at": "2026-06-24T22:00:00+00:00",
      "stadium": "Atlanta",
      "city": "Atlanta",
      "status": "finished",
      "home_score": 4,
      "away_score": 2,
      "home_penalty_score": null,
      "away_penalty_score": null
    },
    {
      "id": 10005,
      "match_number": null,
      "tournament_year": 2026,
      "stage": "Group stage",
      "group_name": "A",
      "home_team_id": 20,
      "away_team_id": 17,
      "kickoff_at": "2026-06-25T01:00:00+00:00",
      "stadium": "Mexico City",
      "city": "Mexico City",
      "status": "finished",
      "home_score": 0,
      "away_score": 3,
      "home_penalty_score": null,
      "away_penalty_score": null
    },
    {
      "id": 10006,
      "match_number": null,
      "tournament_year": 2026,
      "stage": "Group stage",
      "group_name": "A",
      "home_team_id": 18,
      "away_team_id": 19,
      "kickoff_at": "2026-06-25T01:00:00+00:00",
      "stadium": "Monterrey (Guadalupe)",
      "city": "Monterrey (Guadalupe)",
      "status": "finished",
      "home_score": 1,
      "away_score": 0,
      "home_penalty_score": null,
      "away_penalty_score": null
    },
    {
      "id": 10029,
      "match_number": null,
      "tournament_year": 2026,
      "stage": "Group stage",
      "group_name": "E",
      "home_team_id": 34,
      "away_team_id": 35,
      "kickoff_at": "2026-06-25T20:00:00+00:00",
      "stadium": "Philadelphia",
      "city": "Philadelphia",
      "status": "finished",
      "home_score": 0,
      "away_score": 2,
      "home_penalty_score": null,
      "away_penalty_score": null
    },
    {
      "id": 10030,
      "match_number": null,
      "tournament_year": 2026,
      "stage": "Group stage",
      "group_name": "E",
      "home_team_id": 36,
      "away_team_id": 33,
      "kickoff_at": "2026-06-25T20:00:00+00:00",
      "stadium": "New York/New Jersey (East Rutherford)",
      "city": "New York/New Jersey (East Rutherford)",
      "status": "finished",
      "home_score": 2,
      "away_score": 1,
      "home_penalty_score": null,
      "away_penalty_score": null
    },
    {
      "id": 10035,
      "match_number": null,
      "tournament_year": 2026,
      "stage": "Group stage",
      "group_name": "F",
      "home_team_id": 38,
      "away_team_id": 39,
      "kickoff_at": "2026-06-25T23:00:00+00:00",
      "stadium": "Dallas (Arlington)",
      "city": "Dallas (Arlington)",
      "status": "finished",
      "home_score": 1,
      "away_score": 1,
      "home_penalty_score": null,
      "away_penalty_score": null
    },
    {
      "id": 10036,
      "match_number": null,
      "tournament_year": 2026,
      "stage": "Group stage",
      "group_name": "F",
      "home_team_id": 40,
      "away_team_id": 37,
      "kickoff_at": "2026-06-25T23:00:00+00:00",
      "stadium": "Kansas City",
      "city": "Kansas City",
      "status": "finished",
      "home_score": 1,
      "away_score": 3,
      "home_penalty_score": null,
      "away_penalty_score": null
    },
    {
      "id": 10023,
      "match_number": null,
      "tournament_year": 2026,
      "stage": "Group stage",
      "group_name": "D",
      "home_team_id": 32,
      "away_team_id": 29,
      "kickoff_at": "2026-06-26T02:00:00+00:00",
      "stadium": "Los Angeles (Inglewood)",
      "city": "Los Angeles (Inglewood)",
      "status": "finished",
      "home_score": 3,
      "away_score": 2,
      "home_penalty_score": null,
      "away_penalty_score": null
    },
    {
      "id": 10024,
      "match_number": null,
      "tournament_year": 2026,
      "stage": "Group stage",
      "group_name": "D",
      "home_team_id": 30,
      "away_team_id": 31,
      "kickoff_at": "2026-06-26T02:00:00+00:00",
      "stadium": "San Francisco Bay Area (Santa Clara)",
      "city": "San Francisco Bay Area (Santa Clara)",
      "status": "finished",
      "home_score": 0,
      "away_score": 0,
      "home_penalty_score": null,
      "away_penalty_score": null
    },
    {
      "id": 5,
      "match_number": null,
      "tournament_year": 2026,
      "stage": "Group stage",
      "group_name": "I",
      "home_team_id": 1,
      "away_team_id": 2,
      "kickoff_at": "2026-06-26T19:00:00+00:00",
      "stadium": "Boston (Foxborough)",
      "city": "Boston (Foxborough)",
      "status": "finished",
      "home_score": 1,
      "away_score": 4,
      "home_penalty_score": null,
      "away_penalty_score": null
    },
    {
      "id": 6,
      "match_number": null,
      "tournament_year": 2026,
      "stage": "Group stage",
      "group_name": "I",
      "home_team_id": 3,
      "away_team_id": 4,
      "kickoff_at": "2026-06-26T19:00:00+00:00",
      "stadium": "Toronto",
      "city": "Toronto",
      "status": "finished",
      "home_score": 5,
      "away_score": 0,
      "home_penalty_score": null,
      "away_penalty_score": null
    },
    {
      "id": 10047,
      "match_number": null,
      "tournament_year": 2026,
      "stage": "Group stage",
      "group_name": "H",
      "home_team_id": 46,
      "away_team_id": 47,
      "kickoff_at": "2026-06-27T00:00:00+00:00",
      "stadium": "Houston",
      "city": "Houston",
      "status": "finished",
      "home_score": 0,
      "away_score": 0,
      "home_penalty_score": null,
      "away_penalty_score": null
    },
    {
      "id": 10048,
      "match_number": null,
      "tournament_year": 2026,
      "stage": "Group stage",
      "group_name": "H",
      "home_team_id": 48,
      "away_team_id": 45,
      "kickoff_at": "2026-06-27T00:00:00+00:00",
      "stadium": "Guadalajara (Zapopan)",
      "city": "Guadalajara (Zapopan)",
      "status": "finished",
      "home_score": 0,
      "away_score": 1,
      "home_penalty_score": null,
      "away_penalty_score": null
    },
    {
      "id": 10041,
      "match_number": null,
      "tournament_year": 2026,
      "stage": "Group stage",
      "group_name": "G",
      "home_team_id": 42,
      "away_team_id": 43,
      "kickoff_at": "2026-06-27T03:00:00+00:00",
      "stadium": "Seattle",
      "city": "Seattle",
      "status": "finished",
      "home_score": 1,
      "away_score": 1,
      "home_penalty_score": null,
      "away_penalty_score": null
    },
    {
      "id": 10042,
      "match_number": null,
      "tournament_year": 2026,
      "stage": "Group stage",
      "group_name": "G",
      "home_team_id": 44,
      "away_team_id": 41,
      "kickoff_at": "2026-06-27T03:00:00+00:00",
      "stadium": "Vancouver",
      "city": "Vancouver",
      "status": "finished",
      "home_score": 1,
      "away_score": 5,
      "home_penalty_score": null,
      "away_penalty_score": null
    },
    {
      "id": 21,
      "match_number": null,
      "tournament_year": 2026,
      "stage": "Group stage",
      "group_name": "L",
      "home_team_id": 16,
      "away_team_id": 13,
      "kickoff_at": "2026-06-27T21:00:00+00:00",
      "stadium": "New York/New Jersey (East Rutherford)",
      "city": "New York/New Jersey (East Rutherford)",
      "status": "finished",
      "home_score": 0,
      "away_score": 2,
      "home_penalty_score": null,
      "away_penalty_score": null
    },
    {
      "id": 22,
      "match_number": null,
      "tournament_year": 2026,
      "stage": "Group stage",
      "group_name": "L",
      "home_team_id": 14,
      "away_team_id": 15,
      "kickoff_at": "2026-06-27T21:00:00+00:00",
      "stadium": "Philadelphia",
      "city": "Philadelphia",
      "status": "finished",
      "home_score": 2,
      "away_score": 1,
      "home_penalty_score": null,
      "away_penalty_score": null
    },
    {
      "id": 16,
      "match_number": null,
      "tournament_year": 2026,
      "stage": "Group stage",
      "group_name": "K",
      "home_team_id": 12,
      "away_team_id": 9,
      "kickoff_at": "2026-06-27T23:30:00+00:00",
      "stadium": "Miami (Miami Gardens)",
      "city": "Miami (Miami Gardens)",
      "status": "finished",
      "home_score": 0,
      "away_score": 0,
      "home_penalty_score": null,
      "away_penalty_score": null
    },
    {
      "id": 17,
      "match_number": null,
      "tournament_year": 2026,
      "stage": "Group stage",
      "group_name": "K",
      "home_team_id": 10,
      "away_team_id": 11,
      "kickoff_at": "2026-06-27T23:30:00+00:00",
      "stadium": "Atlanta",
      "city": "Atlanta",
      "status": "finished",
      "home_score": 3,
      "away_score": 1,
      "home_penalty_score": null,
      "away_penalty_score": null
    },
    {
      "id": 11,
      "match_number": null,
      "tournament_year": 2026,
      "stage": "Group stage",
      "group_name": "J",
      "home_team_id": 6,
      "away_team_id": 7,
      "kickoff_at": "2026-06-28T02:00:00+00:00",
      "stadium": "Kansas City",
      "city": "Kansas City",
      "status": "finished",
      "home_score": 3,
      "away_score": 3,
      "home_penalty_score": null,
      "away_penalty_score": null
    },
    {
      "id": 12,
      "match_number": null,
      "tournament_year": 2026,
      "stage": "Group stage",
      "group_name": "J",
      "home_team_id": 8,
      "away_team_id": 5,
      "kickoff_at": "2026-06-28T02:00:00+00:00",
      "stadium": "Dallas (Arlington)",
      "city": "Dallas (Arlington)",
      "status": "finished",
      "home_score": 1,
      "away_score": 3,
      "home_penalty_score": null,
      "away_penalty_score": null
    },
    {
      "id": 10073,
      "match_number": 73,
      "tournament_year": 2026,
      "stage": "Round of 32",
      "group_name": null,
      "home_team_id": 18,
      "away_team_id": 21,
      "kickoff_at": "2026-06-28T19:00:00+00:00",
      "stadium": "Los Angeles (Inglewood)",
      "city": "Los Angeles (Inglewood)",
      "status": "finished",
      "home_score": 0,
      "away_score": 1,
      "home_penalty_score": null,
      "away_penalty_score": null
    },
    {
      "id": 10076,
      "match_number": 76,
      "tournament_year": 2026,
      "stage": "Round of 32",
      "group_name": null,
      "home_team_id": 25,
      "away_team_id": 38,
      "kickoff_at": "2026-06-29T17:00:00+00:00",
      "stadium": "Houston",
      "city": "Houston",
      "status": "finished",
      "home_score": 2,
      "away_score": 1,
      "home_penalty_score": null,
      "away_penalty_score": null
    },
    {
      "id": 10074,
      "match_number": 74,
      "tournament_year": 2026,
      "stage": "Round of 32",
      "group_name": null,
      "home_team_id": 33,
      "away_team_id": 30,
      "kickoff_at": "2026-06-29T20:30:00+00:00",
      "stadium": "Boston (Foxborough)",
      "city": "Boston (Foxborough)",
      "status": "finished",
      "home_score": 1,
      "away_score": 1,
      "home_penalty_score": 3,
      "away_penalty_score": 4
    },
    {
      "id": 10075,
      "match_number": 75,
      "tournament_year": 2026,
      "stage": "Round of 32",
      "group_name": null,
      "home_team_id": 37,
      "away_team_id": 26,
      "kickoff_at": "2026-06-30T01:00:00+00:00",
      "stadium": "Monterrey (Guadalupe)",
      "city": "Monterrey (Guadalupe)",
      "status": "finished",
      "home_score": 1,
      "away_score": 1,
      "home_penalty_score": 2,
      "away_penalty_score": 3
    },
    {
      "id": 10078,
      "match_number": 78,
      "tournament_year": 2026,
      "stage": "Round of 32",
      "group_name": null,
      "home_team_id": 35,
      "away_team_id": 1,
      "kickoff_at": "2026-06-30T17:00:00+00:00",
      "stadium": "Dallas (Arlington)",
      "city": "Dallas (Arlington)",
      "status": "scheduled",
      "home_score": null,
      "away_score": null,
      "home_penalty_score": null,
      "away_penalty_score": null
    },
    {
      "id": 10077,
      "match_number": 77,
      "tournament_year": 2026,
      "stage": "Round of 32",
      "group_name": null,
      "home_team_id": 2,
      "away_team_id": 39,
      "kickoff_at": "2026-06-30T21:00:00+00:00",
      "stadium": "New York/New Jersey (East Rutherford)",
      "city": "New York/New Jersey (East Rutherford)",
      "status": "scheduled",
      "home_score": null,
      "away_score": null,
      "home_penalty_score": null,
      "away_penalty_score": null
    },
    {
      "id": 10079,
      "match_number": 79,
      "tournament_year": 2026,
      "stage": "Round of 32",
      "group_name": null,
      "home_team_id": 17,
      "away_team_id": 36,
      "kickoff_at": "2026-07-01T01:00:00+00:00",
      "stadium": "Mexico City",
      "city": "Mexico City",
      "status": "scheduled",
      "home_score": null,
      "away_score": null,
      "home_penalty_score": null,
      "away_penalty_score": null
    },
    {
      "id": 10080,
      "match_number": 80,
      "tournament_year": 2026,
      "stage": "Round of 32",
      "group_name": null,
      "home_team_id": 13,
      "away_team_id": 10,
      "kickoff_at": "2026-07-01T16:00:00+00:00",
      "stadium": "Atlanta",
      "city": "Atlanta",
      "status": "scheduled",
      "home_score": null,
      "away_score": null,
      "home_penalty_score": null,
      "away_penalty_score": null
    },
    {
      "id": 10082,
      "match_number": 82,
      "tournament_year": 2026,
      "stage": "Round of 32",
      "group_name": null,
      "home_team_id": 41,
      "away_team_id": 3,
      "kickoff_at": "2026-07-01T20:00:00+00:00",
      "stadium": "Seattle",
      "city": "Seattle",
      "status": "scheduled",
      "home_score": null,
      "away_score": null,
      "home_penalty_score": null,
      "away_penalty_score": null
    },
    {
      "id": 10081,
      "match_number": 81,
      "tournament_year": 2026,
      "stage": "Round of 32",
      "group_name": null,
      "home_team_id": 29,
      "away_team_id": 22,
      "kickoff_at": "2026-07-02T00:00:00+00:00",
      "stadium": "San Francisco Bay Area (Santa Clara)",
      "city": "San Francisco Bay Area (Santa Clara)",
      "status": "scheduled",
      "home_score": null,
      "away_score": null,
      "home_penalty_score": null,
      "away_penalty_score": null
    },
    {
      "id": 10084,
      "match_number": 84,
      "tournament_year": 2026,
      "stage": "Round of 32",
      "group_name": null,
      "home_team_id": 45,
      "away_team_id": 7,
      "kickoff_at": "2026-07-02T19:00:00+00:00",
      "stadium": "Los Angeles (Inglewood)",
      "city": "Los Angeles (Inglewood)",
      "status": "scheduled",
      "home_score": null,
      "away_score": null,
      "home_penalty_score": null,
      "away_penalty_score": null
    },
    {
      "id": 10083,
      "match_number": 83,
      "tournament_year": 2026,
      "stage": "Round of 32",
      "group_name": null,
      "home_team_id": 9,
      "away_team_id": 14,
      "kickoff_at": "2026-07-02T23:00:00+00:00",
      "stadium": "Toronto",
      "city": "Toronto",
      "status": "scheduled",
      "home_score": null,
      "away_score": null,
      "home_penalty_score": null,
      "away_penalty_score": null
    },
    {
      "id": 10085,
      "match_number": 85,
      "tournament_year": 2026,
      "stage": "Round of 32",
      "group_name": null,
      "home_team_id": 24,
      "away_team_id": 6,
      "kickoff_at": "2026-07-03T03:00:00+00:00",
      "stadium": "Vancouver",
      "city": "Vancouver",
      "status": "scheduled",
      "home_score": null,
      "away_score": null,
      "home_penalty_score": null,
      "away_penalty_score": null
    },
    {
      "id": 10088,
      "match_number": 88,
      "tournament_year": 2026,
      "stage": "Round of 32",
      "group_name": null,
      "home_team_id": 31,
      "away_team_id": 42,
      "kickoff_at": "2026-07-03T18:00:00+00:00",
      "stadium": "Dallas (Arlington)",
      "city": "Dallas (Arlington)",
      "status": "scheduled",
      "home_score": null,
      "away_score": null,
      "home_penalty_score": null,
      "away_penalty_score": null
    },
    {
      "id": 10086,
      "match_number": 86,
      "tournament_year": 2026,
      "stage": "Round of 32",
      "group_name": null,
      "home_team_id": 5,
      "away_team_id": 46,
      "kickoff_at": "2026-07-03T22:00:00+00:00",
      "stadium": "Miami (Miami Gardens)",
      "city": "Miami (Miami Gardens)",
      "status": "scheduled",
      "home_score": null,
      "away_score": null,
      "home_penalty_score": null,
      "away_penalty_score": null
    },
    {
      "id": 10087,
      "match_number": 87,
      "tournament_year": 2026,
      "stage": "Round of 32",
      "group_name": null,
      "home_team_id": 12,
      "away_team_id": 15,
      "kickoff_at": "2026-07-04T01:30:00+00:00",
      "stadium": "Kansas City",
      "city": "Kansas City",
      "status": "scheduled",
      "home_score": null,
      "away_score": null,
      "home_penalty_score": null,
      "away_penalty_score": null
    }
  ]
}